mymathlib_test/__init__.py
mymathlib_test/operations.py
mymathlib_test-0.4.dist-info/METADATA
mymathlib_test-0.4.dist-info/WHEEL
mymathlib_test-0.4.dist-info/top_level.txt
mymathlib_test-0.4.dist-info/RECORD
