Metadata-Version: 2.4
Name: mymathlib_test
Version: 0.4
Summary: A simple math operations library for demo purposes
Author: nani123
Author-email: nanireddy8898@gmail.com
Requires-Python: >=3.6
Dynamic: author
Dynamic: author-email
Dynamic: description
Dynamic: description-content-type
Dynamic: requires-python
Dynamic: summary
